multiversx_sdk_core/__init__.py
multiversx_sdk_core/account.py
multiversx_sdk_core/account_test.py
multiversx_sdk_core/address.py
multiversx_sdk_core/address_test.py
multiversx_sdk_core/bech32.py
multiversx_sdk_core/code_metadata.py
multiversx_sdk_core/code_metadata_test.py
multiversx_sdk_core/codec.py
multiversx_sdk_core/codec_test.py
multiversx_sdk_core/constants.py
multiversx_sdk_core/contract_query.py
multiversx_sdk_core/contract_query_builder.py
multiversx_sdk_core/contract_query_builder_test.py
multiversx_sdk_core/errors.py
multiversx_sdk_core/interfaces.py
multiversx_sdk_core/message.py
multiversx_sdk_core/message_test.py
multiversx_sdk_core/serializer.py
multiversx_sdk_core/token_payment.py
multiversx_sdk_core/token_payment_test.py
multiversx_sdk_core/tokens.py
multiversx_sdk_core/tokens_test.py
multiversx_sdk_core/transaction.py
multiversx_sdk_core/transaction_payload.py
multiversx_sdk_core/transaction_test.py
multiversx_sdk_core/typecheck.py
multiversx_sdk_core/proto/__init__.py
multiversx_sdk_core/proto/transaction.proto
multiversx_sdk_core/proto/transaction_pb2.py
multiversx_sdk_core/proto/transaction_pb2.pyi
multiversx_sdk_core/proto/transaction_serializer.py
multiversx_sdk_core/proto/transaction_serializer_test.py
multiversx_sdk_core/testutils/wallets.py
multiversx_sdk_core/testutils/testdata/adder.wasm
multiversx_sdk_core/testutils/testwallets/alice.pem
multiversx_sdk_core/testutils/testwallets/bob.pem
multiversx_sdk_core/testutils/testwallets/carol.pem
multiversx_sdk_core/testutils/testwallets/frank.pem
multiversx_sdk_core/testutils/testwallets/grace.pem
multiversx_sdk_core/transaction_builders/__init__.py
multiversx_sdk_core/transaction_builders/contract_builders.py
multiversx_sdk_core/transaction_builders/contract_builders_test.py
multiversx_sdk_core/transaction_builders/default_configuration.py
multiversx_sdk_core/transaction_builders/default_configuration_test.py
multiversx_sdk_core/transaction_builders/esdt_builders.py
multiversx_sdk_core-1.0.0.dist-info/METADATA
multiversx_sdk_core-1.0.0.dist-info/WHEEL
multiversx_sdk_core-1.0.0.dist-info/licenses/LICENSE
multiversx_sdk_core-1.0.0.dist-info/RECORD
