Metadata-Version: 2.3
Name: multiversx-sdk-core
Version: 1.0.0
Summary: Deprecated. Instead, use multiversx-sdk.
Project-URL: Homepage, https://github.com/multiversx/mx-sdk-py-core
Author: MultiversX
License-Expression: MIT
License-File: LICENSE
Classifier: Development Status :: 7 - Inactive
Classifier: License :: OSI Approved :: MIT License
Classifier: Operating System :: OS Independent
Classifier: Programming Language :: Python :: 3
Requires-Python: >=3.8
Requires-Dist: protobuf==3.20.2
Requires-Dist: pycryptodomex==3.19.1
